Flask_SQLAlchemy_Caching-1.0.3.dist-info/METADATA
Flask_SQLAlchemy_Caching-1.0.3.dist-info/RECORD
Flask_SQLAlchemy_Caching-1.0.3.dist-info/WHEEL
Flask_SQLAlchemy_Caching-1.0.3.dist-info/top_level.txt
flask_sqlalchemy_caching/__init__.py
flask_sqlalchemy_caching/core.py
