Metadata-Version: 2.1
Name: Flask-SQLAlchemy-Caching
Version: 1.0.3
Summary: CachingQuery implementation to Flask using Flask-SQLAlchemy and Flask-Caching
Home-page: http://www.github.com/bbelyeu/Flask-SQLAlchemy-Caching
Author: Brad Belyeu
Author-email: bradleylamar@gmail.com
License: MIT
Download-URL: https://github.com/bbelyeu/Flask-SQLAlchemy-Caching/archive/1.0.3.zip
Keywords: flask,sqlalchemy,caching,cache
Platform: any
Classifier: Environment :: Web Environment
Classifier: Intended Audience :: Developers
Classifier: License :: OSI Approved :: MIT License
Classifier: Operating System :: OS Independent
Classifier: Programming Language :: Python
Classifier: Programming Language :: Python :: 3
Classifier: Topic :: Internet :: WWW/HTTP :: Dynamic Content
Classifier: Topic :: Software Development :: Libraries :: Python Modules
Requires-Dist: Flask (>=0.12.2)
Requires-Dist: Flask-Caching (>=1.3.2)
Requires-Dist: Flask-SQLAlchemy (>=2.2)
